onkopus/__init__.py
onkopus/__main__.py
onkopus/import_data.py
onkopus/mtb_requests.py
onkopus/onkopus_main.py
onkopus/cli/__init__.py
onkopus/cli/module_mgt.py
onkopus/cli/run_interpretation.py
onkopus/conf/__init__.py
onkopus/conf/config.ini
onkopus/conf/docker_compose.yml
onkopus/conf/docker_config.py
onkopus/conf/read_config.py
onkopus/conf/data/docker-compose.yml
onkopus/conf/docker_compose/alphamissense.yml
onkopus/conf/docker_compose/civic-adapter.yml
onkopus/conf/docker_compose/civic-db.yml
onkopus/conf/docker_compose/clinvar.yml
onkopus/conf/docker_compose/dbnsfp-adapter.yml
onkopus/conf/docker_compose/dbsnp.yml
onkopus/conf/docker_compose/dgidb-adapter.yml
onkopus/conf/docker_compose/dgidb-db.yml
onkopus/conf/docker_compose/gencode-adapter.yml
onkopus/conf/docker_compose/gencode-db.yml
onkopus/conf/docker_compose/gtex-adapter.yml
onkopus/conf/docker_compose/loftool.yml
onkopus/conf/docker_compose/metakb-adapter.yml
onkopus/conf/docker_compose/molecular-features.yml
onkopus/conf/docker_compose/mvp-adapter.yml
onkopus/conf/docker_compose/oncokb.yml
onkopus/conf/docker_compose/onkopus-aggregator.yml
onkopus/conf/docker_compose/onkopus-cache.yml
onkopus/conf/docker_compose/onkopus-database.yml
onkopus/conf/docker_compose/onkopus-interpreter.yml
onkopus/conf/docker_compose/onkopus-plots.yml
onkopus/conf/docker_compose/onkopus-server.yml
onkopus/conf/docker_compose/onkopus-web.yml
onkopus/conf/docker_compose/primateai-adapter.yml
onkopus/conf/docker_compose/protein-analysis.yml
onkopus/conf/docker_compose/revel.yml
onkopus/conf/docker_compose/scannet-adapter.yml
onkopus/conf/docker_compose/uta-adapter.yml
onkopus/conf/docker_compose/uta-database.yml
onkopus/convert/ProteinToGenomic.py
onkopus/convert/TranscriptToGenomic.py
onkopus/convert/__init__.py
onkopus/onkopus_clients/__init__.py
onkopus/onkopus_clients/aggregator_client.py
onkopus/onkopus_clients/biomarker_recognition_client.py
onkopus/onkopus_clients/ccs_gene_fusion_client.py
onkopus-0.6.7.dist-info/LICENSE
onkopus-0.6.7.dist-info/METADATA
onkopus-0.6.7.dist-info/WHEEL
onkopus-0.6.7.dist-info/top_level.txt
onkopus-0.6.7.dist-info/RECORD
