Metadata-Version: 2.1
Name: onkopus
Version: 0.6.7
Summary: Variant interpretation framework to analyze and interpret genetic alterations in cancer
Home-page: https://gitlab.gwdg.de/MedBioinf/mtb/onkopus/onkopus
Author: Nadine S. Kurz
Author-email: nadine.kurz@bioinf.med.uni-goettingen.de
License: GPLv3
Classifier: Programming Language :: Python :: 3
Classifier: License :: OSI Approved :: GNU General Public License v3 (GPLv3)
Classifier: Operating System :: OS Independent
Classifier: Topic :: Scientific/Engineering :: Bio-Informatics
Classifier: Topic :: Scientific/Engineering :: Medical Science Apps.
Classifier: Topic :: Scientific/Engineering :: Artificial Intelligence
Requires-Python: >=3.9
License-File: LICENSE
Requires-Dist: requests
Requires-Dist: numpy
Requires-Dist: matplotlib
Requires-Dist: pandas
Requires-Dist: plotly
Requires-Dist: scikit-learn
Requires-Dist: async-timeout
Requires-Dist: redis
Requires-Dist: pyaml
Requires-Dist: adagenes
